housekeeper/__init__.py
housekeeper/__main__.py
housekeeper/archive/__init__.py
housekeeper/cli/__init__.py
housekeeper/cli/add.py
housekeeper/cli/core.py
housekeeper/cli/delete.py
housekeeper/cli/get.py
housekeeper/cli/include.py
housekeeper/cli/init.py
housekeeper/cli/tables.py
housekeeper/constants.py
housekeeper/date.py
housekeeper/exc.py
housekeeper/files.py
housekeeper/include.py
housekeeper/services/__init__.py
housekeeper/services/file_report_service/__init__.py
housekeeper/services/file_report_service/file_report_service.py
housekeeper/services/file_report_service/utils.py
housekeeper/services/file_service/__init__.py
housekeeper/services/file_service/file_service.py
housekeeper/store/__init__.py
housekeeper/store/api/__init__.py
housekeeper/store/api/schema.py
housekeeper/store/base.py
housekeeper/store/crud/__init__.py
housekeeper/store/crud/create.py
housekeeper/store/crud/read.py
housekeeper/store/crud/update.py
housekeeper/store/database.py
housekeeper/store/filters/__init__.py
housekeeper/store/filters/archive_filters.py
housekeeper/store/filters/bundle_filters.py
housekeeper/store/filters/file_filters.py
housekeeper/store/filters/tag_filters.py
housekeeper/store/filters/version_bundle_filters.py
housekeeper/store/filters/version_filters.py
housekeeper/store/models.py
housekeeper/store/store.py
housekeeper-4.13.15.dist-info/METADATA
housekeeper-4.13.15.dist-info/WHEEL
housekeeper-4.13.15.dist-info/entry_points.txt
housekeeper-4.13.15.dist-info/licenses/LICENSE
housekeeper-4.13.15.dist-info/RECORD
