Metadata-Version: 2.4
Name: housekeeper
Version: 4.13.15
Summary: File data orchestrator
License: MIT
License-File: LICENSE
Author: henrikstranneheim
Author-email: henrik.stranneheim@scilifelab.se
Requires-Python: >=3.11
Classifier: License :: OSI Approved :: MIT License
Classifier: Programming Language :: Python :: 3
Classifier: Programming Language :: Python :: 3.11
Classifier: Programming Language :: Python :: 3.12
Classifier: Programming Language :: Python :: 3.13
Classifier: Programming Language :: Python :: 3.14
Requires-Dist: PyMySQL
Requires-Dist: PyYAML
Requires-Dist: SQLAlchemy
Requires-Dist: click
Requires-Dist: coloredlogs
Requires-Dist: cryptography
Requires-Dist: marshmallow
Requires-Dist: rich
Requires-Dist: setuptools
